chik_puzzles_py/__init__.py
chik_puzzles_py/manage_klvm.py
chik_puzzles_py/programs.py
chik_puzzles_py/tests/__init__.py
chik_puzzles_py/tests/test_import.py
chik_puzzles_py-0.20.2.dist-info/LICENSE
chik_puzzles_py-0.20.2.dist-info/METADATA
chik_puzzles_py-0.20.2.dist-info/WHEEL
chik_puzzles_py-0.20.2.dist-info/RECORD
