Metadata-Version: 2.3
Name: chik_puzzles_py
Version: 0.20.2
Summary: A collection of the currently deployed ChikLisp puzzles.
Author: Matt Howard
Author-email: matt@chiknetwork.com
Requires-Python: >=3.8,<4.0
Classifier: Programming Language :: Python :: 3
Classifier: Programming Language :: Python :: 3.8
Classifier: Programming Language :: Python :: 3.9
Classifier: Programming Language :: Python :: 3.10
Classifier: Programming Language :: Python :: 3.11
Classifier: Programming Language :: Python :: 3.12
Classifier: Programming Language :: Python :: 3.13
Requires-Dist: klvm-rs (>=0.2.3,<0.3.0)
Requires-Dist: klvm-tools-rs (>=0.1.45,<0.2.0)
Requires-Dist: pytest (>=8.3.3,<9.0.0)
